{"uuid":"3d977306-1835-11ef-9a21-cfd8fbf76dbb","trade_conditions":["24","12"],"price":429.4,"symbol":"MSFT","trade_timestamp":"2024-05-22T14:17:17.818+02:00","volume":2.0,"ingest_timestamp":"2024-05-22T14:17:21.011+02:00"}
{"uuid":"3d977307-1835-11ef-9a21-cfd8fbf76dbb","trade_conditions":["1","24","12"],"price":429.4,"symbol":"MSFT","trade_timestamp":"2024-05-22T14:17:17.818+02:00","volume":2.0,"ingest_timestamp":"2024-05-22T14:17:21.011+02:00"}
{"uuid":"3d977308-1835-11ef-9a21-cfd8fbf76dbb","trade_conditions":["1","24","12"],"price":176.48,"symbol":"GOOGL","trade_timestamp":"2024-05-22T14:17:18.581+02:00","volume":10.0,"ingest_timestamp":"2024-05-22T14:17:21.011+02:00"}
